nasa_sbm/__init__.py
nasa_sbm/configuration.py
nasa_sbm/event.py
nasa_sbm/model.py
nasa_sbm/satellite.py
nasa_sbm/utils.py
nasa_sbm-0.0.1.dist-info/LICENSE
nasa_sbm-0.0.1.dist-info/METADATA
nasa_sbm-0.0.1.dist-info/WHEEL
nasa_sbm-0.0.1.dist-info/top_level.txt
nasa_sbm-0.0.1.dist-info/RECORD
