Metadata-Version: 2.1
Name: nasa-sbm
Version: 0.0.1
Summary: An implementation of the python-sbm
Home-page: https://github.com/ReeceHumphreys/python-sbm
Author: Reece Humphreys
Author-email: reecewh@icloud.com
License: UNKNOWN
Project-URL: Bug Tracker, https://github.com/ReeceHumphreys/python-sbm/issues
Platform: UNKNOWN
Classifier: Programming Language :: Python :: 3
Classifier: License :: OSI Approved :: MIT License
Classifier: Operating System :: OS Independent
Requires-Python: >=3.6
License-File: LICENSE
Requires-Dist: numpy (>=1)
Requires-Dist: PyYAML (>=4)
Provides-Extra: docs
Requires-Dist: sphinx ; extra == 'docs'
Requires-Dist: myst-parser ; extra == 'docs'
